.DS_Store
rave/__init__.py
rave/height_functions.py
rave/image_class.py
rave/lib.py
rave/linecut_functions.py
rave/ring_functions.py
rave/short_functions.py
rave/test_link.py
rave-1.0.0.dist-info/LICENSE
rave-1.0.0.dist-info/METADATA
rave-1.0.0.dist-info/WHEEL
rave-1.0.0.dist-info/top_level.txt
rave-1.0.0.dist-info/RECORD
