Metadata-Version: 2.1
Name: rave
Version: 1.0.0
Summary: Modelling the structure of edge-on debris disks.
Home-page: https://github.com/yinuohan/Rave
Author: Yinuo Han
Author-email: yh458@cam.ac.uk
License: GNU AFFERO GENERAL PUBLIC LICENSE 3.0
Platform: UNKNOWN
Requires-Dist: numpy
Requires-Dist: matplotlib
Requires-Dist: astropy
Requires-Dist: scipy
